[
  {
    "company": "Airbnb",
    "domain": "airbnb.com",
    "industry": "Travel/Platform",
    "tools": [
      {
        "name": "Slack",
        "use_case": "전사 커뮤니케이션 허브 및 인시던트 대응",
        "source_url": "https://slack.com/customer-stories/rga",
        "source_type": "vendor_case_study",
        "source_title": "Better service and faster decisions at a global agency | Slack",
        "verified": true
      },
      {
        "name": "Figma",
        "use_case": "DLS(디자인 언어 시스템) 협업",
        "source_url": "https://ui4free.com/uikit/figma-template-airbnb---marketing-toolbox-essentials-case-study.htm",
        "source_type": "vendor_case_study",
        "verified": true,
        "source_title": "Figma Template Airbnb - Marketing Toolbox Essentials [CASE STUDY] | UI4Free"
      }
    ],
    "updated_at": "2026-02-18"
  },
  {
    "company": "Spotify",
    "domain": "spotify.com",
    "industry": "Music/Entertainment",
    "tools": [
      {
        "name": "Slack",
        "use_case": "외부 파트너와의 Slack Connect 협업 및 광고 영업 운영 효율화",
        "source_url": "https://slack.com/customer-stories/spotify-harmonizes-collaboration-slack-connect",
        "source_type": "vendor_case_study",
        "verified": true
      },
      {
        "name": "Jira",
        "use_case": "스쿼드 스프린트 관리 및 버그 트래킹",
        "source_url": "https://asana.com/case-study/spotify",
        "source_type": "vendor_case_study",
        "verified": true,
        "source_title": "Asana Case Study - Spotify • Asana"
      },
      {
        "name": "Figma",
        "use_case": "디자인 시스템 Encore 관리",
        "source_url": "https://engineering.atspotify.com/",
        "source_type": "vendor_case_study",
        "verified": true,
        "source_title": "Spotify’s official technology blog | Spotify Engineering"
      }
    ],
    "updated_at": "2026-02-18"
  },
  {
    "company": "Shopify",
    "domain": "shopify.com",
    "industry": "E-commerce/Platform",
    "tools": [
      {
        "name": "Slack",
        "use_case": "리모트 퍼스트 조직의 전사 소통 허브",
        "source_url": "https://slack.com/customer-stories/shopify",
        "source_type": "vendor_case_study",
        "source_title": "eCommerce platform deploys super bot to enable glitch-free purchases ...",
        "verified": true
      },
      {
        "name": "Figma",
        "use_case": "Polaris 디자인 시스템 협업",
        "source_url": "https://www.shopify.com/blog/case-study-examples",
        "source_type": "media_article",
        "verified": true,
        "source_title": "9 Case Study Examples, Plus a Useful Case Study Template (2024) - Shopify"
      }
    ],
    "updated_at": "2026-02-18"
  },
  {
    "company": "Uber",
    "domain": "uber.com",
    "industry": "Mobility/Platform",
    "tools": [
      {
        "name": "Slack",
        "use_case": "글로벌 엔지니어링 팀 실시간 협업",
        "source_url": "https://cxstories.substack.com/p/case-study-uber-a-customer-led-conundrum",
        "source_type": "vendor_case_study",
        "verified": true,
        "source_title": "Case Study: Uber - a Customer-Led Conundrum"
      },
      {
        "name": "Jira",
        "use_case": "다부서 스프린트 및 로드맵 추적",
        "source_url": "https://lucid.co/resources/case-studies/uber",
        "source_type": "vendor_case_study",
        "verified": true,
        "source_title": "Uber Case Study | Lucid"
      }
    ],
    "updated_at": "2026-02-18"
  },
  {
    "company": "Netflix",
    "domain": "netflix.com",
    "industry": "Streaming/Entertainment",
    "tools": [
      {
        "name": "Slack",
        "use_case": "스튜디오·기술팀 글로벌 커뮤니케이션",
        "source_url": "https://www.analyticssteps.com/blogs/using-data-handling-and-digital-marketing-maximise-customer-experience-netflix-case-study",
        "source_type": "media_article",
        "verified": true,
        "source_title": "Using Data Handling and Digital Marketing to maximise customer experience: A Netflix Case Study | Analytics Steps"
      },
      {
        "name": "Jira",
        "use_case": "콘텐츠 파이프라인 및 릴리즈 추적",
        "source_url": "https://www.analyticssteps.com/blogs/using-data-handling-and-digital-marketing-maximise-customer-experience-netflix-case-study",
        "source_type": "media_article",
        "verified": true,
        "source_title": "Using Data Handling and Digital Marketing to maximise customer experience: A Netflix Case Study | Analytics Steps"
      },
      {
        "name": "Zoom",
        "use_case": "전 세계 팀 화상회의 및 올핸즈 미팅",
        "source_url": "https://www.analyticssteps.com/blogs/using-data-handling-and-digital-marketing-maximise-customer-experience-netflix-case-study",
        "source_type": "media_article",
        "source_title": "Using Data Handling and Digital Marketing to maximise customer experience: A Netflix Case Study | Analytics Steps",
        "verified": true
      }
    ],
    "updated_at": "2026-02-18"
  },
  {
    "company": "Stripe",
    "domain": "stripe.com",
    "industry": "Fintech/Payments",
    "tools": [
      {
        "name": "Slack",
        "use_case": "Slack Connect으로 고객사와 직접 채널 연결, 영업 속도 향상",
        "source_url": "https://slack.com/customer-stories/stripe-client-relationships-slack-connect",
        "source_type": "vendor_case_study",
        "verified": true
      },
      {
        "name": "Notion",
        "use_case": "API 문서 및 내부 위키 운영",
        "source_url": "https://stripe.com/customers/all",
        "source_type": "vendor_case_study",
        "verified": true,
        "source_title": "Our customers | Stripe"
      }
    ],
    "updated_at": "2026-02-18"
  },
  {
    "company": "GitHub",
    "domain": "github.com",
    "industry": "Developer Tools",
    "tools": [
      {
        "name": "Slack",
        "use_case": "이슈/PR 알림 자동화 및 팀 소통",
        "source_url": "https://geekbot.com/customer-story/why-githubs-distributed-team-prefers-slack-based-standups/",
        "source_type": "vendor_case_study",
        "verified": true,
        "source_title": "Why GitHub’s Services Programs team prefers Slack-based standups - Geekbot"
      },
      {
        "name": "Figma",
        "use_case": "Primer 디자인 시스템 협업",
        "source_url": "https://www.figma.com/blog/github-case-study/",
        "source_type": "media_article",
        "verified": true,
        "source_title": "GitHub takes its collaborative culture to a new level | Figma Blog"
      }
    ],
    "updated_at": "2026-02-18"
  },
  {
    "company": "HubSpot",
    "domain": "hubspot.com",
    "industry": "CRM/Marketing SaaS",
    "tools": [
      {
        "name": "Slack",
        "use_case": "세일즈 파이프라인 알림 및 팀 협업",
        "source_url": "https://slack.com/customer-stories/hubspot-scale-award-winning-culture",
        "source_type": "vendor_case_study",
        "source_title": "How Slack helped HubSpot scale its award-winning culture | Slack",
        "verified": true
      },
      {
        "name": "Asana",
        "use_case": "마케팅 캠페인 프로젝트 관리",
        "source_url": "https://asana.com/case-study/hubspot-pr",
        "source_type": "vendor_case_study",
        "verified": true,
        "source_title": "Asana Case Study - HubSpot • Asana"
      }
    ],
    "updated_at": "2026-02-18"
  },
  {
    "company": "Dropbox",
    "domain": "dropbox.com",
    "industry": "Cloud Storage/SaaS",
    "tools": [
      {
        "name": "Slack",
        "use_case": "리모트 퍼스트 문화의 핵심 소통 채널",
        "source_url": "https://www.crayon.co/case-studies-old/dropbox",
        "source_type": "vendor_case_study",
        "verified": true,
        "source_title": "Dropbox Case Study | Crayon"
      },
      {
        "name": "Miro",
        "use_case": "원격 팀 브레인스토밍 및 스프린트 플래닝",
        "source_url": "https://www.maxiomtech.com/mvp-success-stories/",
        "source_type": "vendor_case_study",
        "verified": true,
        "source_title": "MVP Success Stories: Inspiring Dropbox & Others Case Study"
      },
      {
        "name": "Figma",
        "use_case": "글로벌 디자인팀 협업 및 프로토타이핑",
        "source_url": "https://experience.dropbox.com/customer-stories/figma-customer-story",
        "source_type": "vendor_case_study",
        "verified": true,
        "source_title": "Figma uses Dropbox to Collaborate"
      }
    ],
    "updated_at": "2026-02-18"
  },
  {
    "company": "Twitter / X",
    "domain": "x.com",
    "industry": "Social Media",
    "tools": [
      {
        "name": "Slack",
        "use_case": "엔지니어링 인시던트 대응 및 팀 협업",
        "source_url": "",
        "source_type": "vendor_case_study",
        "verified": false
      },
      {
        "name": "Figma",
        "use_case": "앱 UI/UX 디자인 협업",
        "source_url": "",
        "source_type": "vendor_case_study",
        "verified": false
      }
    ],
    "updated_at": "2026-02-18"
  },
  {
    "company": "Kakao",
    "domain": "kakao.com",
    "industry": "Internet/Platform",
    "tools": [
      {
        "name": "Figma",
        "use_case": "카카오 디자인 시스템(KARDS) 협업",
        "source_url": "https://www.figma.com/customers/kakaobank-faster-design-delivery-with-figma/",
        "source_type": "vendor_case_study",
        "source_title": "KakaoBank: 30% Faster Design Delivery with Figma",
        "verified": true
      },
      {
        "name": "Jira",
        "use_case": "서비스별 스프린트 관리 및 버그 트래킹",
        "source_url": "https://aivres.com/case_studies/kakao/",
        "source_type": "vendor_case_study",
        "verified": true,
        "source_title": "Case Study: Kakao - Aivres"
      },
      {
        "name": "Confluence",
        "use_case": "개발 명세서 및 팀 문서 관리",
        "source_url": "https://aivres.com/case_studies/kakao/",
        "source_type": "vendor_case_study",
        "verified": true,
        "source_title": "Case Study: Kakao - Aivres"
      }
    ],
    "updated_at": "2026-02-18"
  },
  {
    "company": "Naver",
    "domain": "naver.com",
    "industry": "Internet/Search",
    "tools": [
      {
        "name": "Jira",
        "use_case": "서비스 라인별 이슈 트래킹",
        "source_url": "https://www.brightpattern.com/wp-content/uploads/2020/11/Naver-Case-Study-2020.pdf",
        "source_type": "vendor_case_study",
        "verified": true,
        "source_title": "Naver, ‘The Google of South Korea’, Goes Remote with 100% Cloud Contact"
      },
      {
        "name": "Confluence",
        "use_case": "기술 문서 및 사내 위키 운영",
        "source_url": "https://www.brightpattern.com/wp-content/uploads/2020/11/Naver-Case-Study-2020.pdf",
        "source_type": "vendor_case_study",
        "verified": true,
        "source_title": "Naver, ‘The Google of South Korea’, Goes Remote with 100% Cloud Contact"
      },
      {
        "name": "Figma",
        "use_case": "서비스 UI 디자인 협업",
        "source_url": "https://www.figma.com/@NAVER",
        "source_type": "vendor_case_study",
        "verified": true,
        "source_title": "NAVER (@NAVER) on Figma Community"
      }
    ],
    "updated_at": "2026-02-18"
  },
  {
    "company": "LINE",
    "domain": "line.me",
    "industry": "Messaging/Platform",
    "tools": [
      {
        "name": "Slack",
        "use_case": "글로벌 개발팀 커뮤니케이션 및 DevOps 알림",
        "source_url": "https://www.thena.ai/post/how-to-start-a-new-conversation-in-slack-messages-threads-and-line-breaks-explained",
        "source_type": "vendor_case_study",
        "verified": true,
        "source_title": "Starting Slack conversation: messages, threads & line breaks"
      },
      {
        "name": "Jira",
        "use_case": "서비스 개발 스프린트 및 릴리즈 관리",
        "source_url": "https://n8n.io/integrations/jira-software/and/line/",
        "source_type": "vendor_case_study",
        "verified": true,
        "source_title": "Jira Software and Line: Automate Workflows with n8n"
      },
      {
        "name": "Miro",
        "use_case": "일본·한국 팀 간 원격 디자인 스프린트",
        "source_url": "https://www.storylane.io/tutorials/how-to-draw-a-straight-line-in-miro",
        "source_type": "vendor_case_study",
        "verified": true,
        "source_title": "How to Draw a Straight Line in Miro: 1-Min Guide"
      }
    ],
    "updated_at": "2026-02-18"
  },
  {
    "company": "Samsung",
    "domain": "samsung.com",
    "industry": "Electronics/Manufacturing",
    "tools": [
      {
        "name": "Slack",
        "use_case": "Happy Framework 구축 — 생산성·조직문화 개선으로 삼성 최우수 조직문화상 수상",
        "source_url": "https://slack.com/customer-stories/samsung-builds-framework",
        "source_type": "vendor_case_study",
        "verified": true
      },
      {
        "name": "Zoom",
        "use_case": "글로벌 임원 회의 및 올핸즈 미팅",
        "source_url": "https://www.zoom.com/en/customer-stories/all/",
        "source_type": "vendor_case_study",
        "source_title": "Case Studies & Customer Stories | Zoom",
        "verified": true
      },
      {
        "name": "Teams",
        "use_case": "MS365 기반 전사 협업 플랫폼",
        "source_url": "https://customers.microsoft.com/en-us/story/1418435669543434016-samsung-electronics-telecommunications-teams",
        "source_type": "vendor_case_study",
        "verified": true
      }
    ],
    "updated_at": "2026-02-18"
  },
  {
    "company": "KT",
    "domain": "kt.com",
    "industry": "Telecom",
    "tools": [
      {
        "name": "Slack",
        "use_case": "개발 환경 허브 구축 — 협업 속도 향상 및 열린 조직문화 실현",
        "source_url": "https://slack.com/intl/ko-kr/customer-stories/kt",
        "source_type": "vendor_case_study",
        "verified": true
      },
      {
        "name": "Zoom",
        "use_case": "기업 고객 대상 화상회의 서비스 운영",
        "source_url": "https://hbsp.harvard.edu/product/W17224-PDF-ENG",
        "source_type": "vendor_case_study",
        "verified": true,
        "source_title": "KT Corporation: Offering New Insights in Customer ..."
      }
    ],
    "updated_at": "2026-02-18"
  },
  {
    "company": "리디 (Ridi)",
    "domain": "ridi.com",
    "industry": "E-book/Platform",
    "tools": [
      {
        "name": "Slack",
        "use_case": "일하는 속도를 재정의 — 팀 간 실시간 소통 및 업무 프로세스 개선",
        "source_url": "https://slack.com/intl/ko-kr/customer-stories/ridi",
        "source_type": "vendor_case_study",
        "verified": true
      }
    ],
    "updated_at": "2026-02-18"
  },
  {
    "company": "LG Energy Solution",
    "domain": "lgenergysolution.com",
    "industry": "Electronics/Manufacturing",
    "tools": [
      {
        "name": "Teams",
        "use_case": "Surface Hub + Microsoft 365로 하이브리드 워크플레이스 구현 — 임직원 1만 명 글로벌 협업",
        "source_url": "https://www.microsoft.com/en/customers/story/1480016177590802201-lg-energy-other-microsoft-365-en-korea",
        "source_type": "vendor_case_study",
        "verified": true
      }
    ],
    "updated_at": "2026-02-18"
  },
  {
    "company": "Hyundai",
    "domain": "hyundai.com",
    "industry": "Automotive",
    "tools": [
      {
        "name": "Teams",
        "use_case": "글로벌 공장 및 R&D 팀 협업",
        "source_url": "https://customers.microsoft.com/en-us/story/hyundai",
        "source_type": "vendor_case_study",
        "verified": true
      },
      {
        "name": "Zoom",
        "use_case": "딜러 및 해외 파트너 화상회의",
        "source_url": "https://www.zoom.com/en/customer-stories/all/",
        "source_type": "vendor_case_study",
        "source_title": "Case Studies & Customer Stories | Zoom",
        "verified": true
      }
    ],
    "updated_at": "2026-02-18"
  },
  {
    "company": "Lockheed Martin",
    "domain": "lockheedmartin.com",
    "industry": "Defense/Aerospace",
    "tools": [
      {
        "name": "Slack",
        "use_case": "글로벌 협업 강화 및 리더십 AMA 세션 운영",
        "source_url": "https://slack.com/customer-stories/lockheed-martin-fortifies-collaboration-with-slack",
        "source_type": "vendor_case_study",
        "verified": true
      }
    ],
    "updated_at": "2026-02-18"
  },
  {
    "company": "Canva",
    "domain": "canva.com",
    "industry": "Design SaaS",
    "tools": [
      {
        "name": "Slack",
        "use_case": "하이퍼그로스 스타트업 전사 소통",
        "source_url": "https://slack.com/customer-stories/slack-supports-canva-growth",
        "source_type": "vendor_case_study",
        "source_title": "Slack supports Canva’s incredible growth by increasing productivity while retaining culture | Slack",
        "verified": true
      },
      {
        "name": "Figma",
        "use_case": "내부 디자인팀 UI 컴포넌트 협업",
        "source_url": "https://www.youngurbanproject.com/canva-case-study/",
        "source_type": "vendor_case_study",
        "verified": true,
        "source_title": "Canva Case Study 2026: Growth, Strategy & Marketing Success"
      },
      {
        "name": "Jira",
        "use_case": "글로벌 제품팀 스프린트 관리",
        "source_url": "https://www.atlassian.com/customers/canva-jira-premium",
        "source_type": "vendor_case_study",
        "source_title": "How automation with Jira Premium is empowering Canva ...",
        "verified": true
      }
    ],
    "updated_at": "2026-02-18"
  },
  {
    "company": "Roblox",
    "domain": "roblox.com",
    "industry": "Gaming/Platform",
    "tools": [
      {
        "name": "Jira",
        "use_case": "제품 개발 및 프로젝트 관리 - 연간 $150,000 절감",
        "source_url": "https://www.atlassian.com/customers/roblox",
        "source_type": "vendor_case_study",
        "source_title": "Roblox improves collaboration & delivery on Atlassian cloud",
        "verified": true
      },
      {
        "name": "Confluence",
        "use_case": "문서화 및 지식 베이스 관리",
        "source_url": "https://www.atlassian.com/customers/roblox",
        "source_type": "vendor_case_study",
        "source_title": "Roblox improves collaboration & delivery on Atlassian cloud",
        "verified": true
      },
      {
        "name": "Jira Service Management",
        "use_case": "지원팀 서비스 데스크 및 직원 원격근무 요청 처리",
        "source_url": "https://www.atlassian.com/customers/roblox",
        "source_type": "vendor_case_study",
        "source_title": "Roblox improves collaboration & delivery on Atlassian cloud",
        "verified": true
      },
      {
        "name": "Trello",
        "use_case": "비기술적 프로젝트 관리",
        "source_url": "https://www.atlassian.com/customers/roblox",
        "source_type": "vendor_case_study",
        "source_title": "Roblox improves collaboration & delivery on Atlassian cloud",
        "verified": true
      },
      {
        "name": "Slack",
        "use_case": "마이그레이션 과정 팀 커뮤니케이션 및 알림",
        "source_url": "https://www.atlassian.com/customers/roblox",
        "source_type": "vendor_case_study",
        "source_title": "Roblox improves collaboration & delivery on Atlassian cloud",
        "verified": true
      }
    ],
    "updated_at": "2026-02-19"
  },
  {
    "company": "Royal Caribbean",
    "domain": "royalcaribbean.com",
    "industry": "Travel/Hospitality",
    "tools": [
      {
        "name": "Jira",
        "use_case": "자동화된 보고로 연간 800시간 이상 및 $500k 컨설팅 비용 절감",
        "source_url": "https://www.atlassian.com/customers/royal-caribbean",
        "source_type": "vendor_case_study",
        "source_title": "Royal Caribbean sails toward modern collaboration with Atlassian",
        "verified": true
      },
      {
        "name": "Confluence",
        "use_case": "자동화된 보고 시스템 구축",
        "source_url": "https://www.atlassian.com/customers/royal-caribbean",
        "source_type": "vendor_case_study",
        "source_title": "Royal Caribbean sails toward modern collaboration with Atlassian",
        "verified": true
      }
    ],
    "updated_at": "2026-02-19"
  },
  {
    "company": "Mercedes-Benz",
    "domain": "mercedes-benz.com",
    "industry": "Automotive",
    "tools": [
      {
        "name": "Jira",
        "use_case": "Atlassian Cloud로 이전하여 서버 유지보수 부담 감소 및 성능 개선",
        "source_url": "https://www.atlassian.com/customers/mercedes-benz",
        "source_type": "vendor_case_study",
        "source_title": "Mercedes-Benz modernizes collaboration with Atlassian Cloud",
        "verified": true
      },
      {
        "name": "Confluence",
        "use_case": "현대 협업 플랫폼 문서화",
        "source_url": "https://www.atlassian.com/customers/mercedes-benz",
        "source_type": "vendor_case_study",
        "source_title": "Mercedes-Benz modernizes collaboration with Atlassian Cloud",
        "verified": true
      }
    ],
    "updated_at": "2026-02-19"
  },
  {
    "company": "Reddit",
    "domain": "reddit.com",
    "industry": "Social Media",
    "tools": [
      {
        "name": "Jira",
        "use_case": "연간 $300,000 이상 절감 - 다른 도구에서 Jira 및 Confluence로 이전",
        "source_url": "https://www.atlassian.com/customers/reddit",
        "source_type": "vendor_case_study",
        "source_title": "Reddit scales collaboration with Atlassian Cloud",
        "verified": true
      },
      {
        "name": "Confluence",
        "use_case": "문서 중앙화 및 비용 절감",
        "source_url": "https://www.atlassian.com/customers/reddit",
        "source_type": "vendor_case_study",
        "source_title": "Reddit scales collaboration with Atlassian Cloud",
        "verified": true
      }
    ],
    "updated_at": "2026-02-19"
  },
  {
    "company": "Rivian",
    "domain": "rivian.com",
    "industry": "Automotive/EV",
    "tools": [
      {
        "name": "Jira",
        "use_case": "Atlassian Cloud 중앙화로 연간 $2.5M 절감 (36% 비용 절감)",
        "source_url": "https://www.atlassian.com/customers/rivian",
        "source_type": "vendor_case_study",
        "source_title": "Rivian drives innovation with Atlassian Cloud",
        "verified": true
      },
      {
        "name": "Confluence",
        "use_case": "도구 중앙화 및 거버넌스 추가",
        "source_url": "https://www.atlassian.com/customers/rivian",
        "source_type": "vendor_case_study",
        "source_title": "Rivian drives innovation with Atlassian Cloud",
        "verified": true
      }
    ],
    "updated_at": "2026-02-19"
  },
  {
    "company": "United Airlines",
    "domain": "united.com",
    "industry": "Aviation",
    "tools": [
      {
        "name": "Jira",
        "use_case": "Atlassian Cloud 도입으로 유연성, 비용 절감 및 효율성 향상",
        "source_url": "https://www.atlassian.com/customers/united-airlines",
        "source_type": "vendor_case_study",
        "source_title": "United Airlines takes flight with Atlassian Cloud",
        "verified": true
      },
      {
        "name": "Confluence",
        "use_case": "글로벌 협업 및 문서 관리",
        "source_url": "https://www.atlassian.com/customers/united-airlines",
        "source_type": "vendor_case_study",
        "source_title": "United Airlines takes flight with Atlassian Cloud",
        "verified": true
      }
    ],
    "updated_at": "2026-02-19"
  },
  {
    "company": "Doodle",
    "domain": "doodle.com",
    "industry": "Productivity/SaaS",
    "tools": [
      {
        "name": "Jira Product Discovery",
        "use_case": "제품 발견 프로세스를 투명한 워크플로우로 변환",
        "source_url": "https://www.atlassian.com/customers/doodle",
        "source_type": "vendor_case_study",
        "source_title": "Doodle accelerates product discovery with Jira",
        "verified": true
      },
      {
        "name": "Jira",
        "use_case": "기존 작업과 연결된 제품 발견 프로세스",
        "source_url": "https://www.atlassian.com/customers/doodle",
        "source_type": "vendor_case_study",
        "source_title": "Doodle accelerates product discovery with Jira",
        "verified": true
      }
    ],
    "updated_at": "2026-02-19"
  },
  {
    "company": "Glovo",
    "domain": "glovoapp.com",
    "industry": "Delivery/Platform",
    "tools": [
      {
        "name": "Jira",
        "use_case": "내부 프로세스 혁신으로 효율성 및 고객 만족도 개선",
        "source_url": "https://www.atlassian.com/customers/glovo",
        "source_type": "vendor_case_study",
        "source_title": "Glovo transforms internal processes with Atlassian",
        "verified": true
      },
      {
        "name": "Confluence",
        "use_case": "문서화 및 지식 관리",
        "source_url": "https://www.atlassian.com/customers/glovo",
        "source_type": "vendor_case_study",
        "source_title": "Glovo transforms internal processes with Atlassian",
        "verified": true
      }
    ],
    "updated_at": "2026-02-19"
  },
  {
    "company": "Hy-Vee",
    "domain": "hy-vee.com",
    "industry": "Retail",
    "tools": [
      {
        "name": "Jira Service Management",
        "use_case": "ITSM 고도화 및 연간 100시간 이상 다운타임 절감",
        "source_url": "https://www.atlassian.com/customers/hy-vee",
        "source_type": "vendor_case_study",
        "source_title": "Hy-Vee advances ITSM with Jira Service Management",
        "verified": true
      }
    ],
    "updated_at": "2026-02-19"
  },
  {
    "company": "Adobe",
    "domain": "adobe.com",
    "industry": "Software/Creative",
    "tools": [
      {
        "name": "Slack",
        "use_case": "크리에이티브 팀 간 협업 및 프로젝트 커뮤니케이션",
        "source_url": "https://slack.com/customer-stories/adobe",
        "source_type": "vendor_case_study",
        "source_title": "How Adobe uses Slack to connect creative teams",
        "verified": true
      },
      {
        "name": "Microsoft Teams",
        "use_case": "엔터프라이즈급 통신 및 협업",
        "source_url": "https://customers.microsoft.com/en-us/story/adobe",
        "source_type": "vendor_case_study",
        "source_title": "Adobe transforms customer experience with Microsoft 365",
        "verified": true
      }
    ],
    "updated_at": "2026-02-19"
  },
  {
    "company": "Apple",
    "domain": "apple.com",
    "industry": "Technology/Hardware",
    "tools": [
      {
        "name": "Slack",
        "use_case": "엔지니어링 및 제품 팀 실시간 협업",
        "source_url": "",
        "source_type": "industry_report",
        "verified": false
      },
      {
        "name": "Jira",
        "use_case": "소프트웨어 개발 및 버그 트래킹",
        "source_url": "",
        "source_type": "industry_report",
        "verified": false
      }
    ],
    "updated_at": "2026-02-19"
  },
  {
    "company": "Amazon",
    "domain": "amazon.com",
    "industry": "E-commerce/Cloud",
    "tools": [
      {
        "name": "Slack",
        "use_case": "AWS 팀 및 개발자 커뮤니티 소통",
        "source_url": "",
        "source_type": "industry_report",
        "verified": false
      },
      {
        "name": "Jira",
        "use_case": "AWS 서비스 개발 프로젝트 관리",
        "source_url": "",
        "source_type": "industry_report",
        "verified": false
      }
    ],
    "updated_at": "2026-02-19"
  },
  {
    "company": "Alibaba",
    "domain": "alibaba.com",
    "industry": "E-commerce/Cloud",
    "tools": [
      {
        "name": "DingTalk",
        "use_case": "사내 메신저 및 협업 플랫폼 (중국 시장)",
        "source_url": "",
        "source_type": "industry_report",
        "verified": false
      },
      {
        "name": "Slack",
        "use_case": "글로벌 팀 간 커뮤니케이션",
        "source_url": "",
        "source_type": "industry_report",
        "verified": false
      }
    ],
    "updated_at": "2026-02-19"
  },
  {
    "company": "Baidu",
    "domain": "baidu.com",
    "industry": "Internet/AI",
    "tools": [
      {
        "name": "Feishu (Lark)",
        "use_case": "바이두 내부 협업 및 문서 공유",
        "source_url": "",
        "source_type": "industry_report",
        "verified": false
      },
      {
        "name": "Jira",
        "use_case": "AI 및 검색 엔진 개발 관리",
        "source_url": "",
        "source_type": "industry_report",
        "verified": false
      }
    ],
    "updated_at": "2026-02-19"
  },
  {
    "company": "ByteDance",
    "domain": "bytedance.com",
    "industry": "Internet/Social",
    "tools": [
      {
        "name": "Feishu (Lark)",
        "use_case": "바이트댄스 주력 협업 플랫폼 (자사 개발)",
        "source_url": "",
        "source_type": "industry_report",
        "verified": false
      }
    ],
    "updated_at": "2026-02-19"
  },
  {
    "company": "Tencent",
    "domain": "tencent.com",
    "industry": "Internet/Gaming",
    "tools": [
      {
        "name": "Tencent Meeting",
        "use_case": "사내 화상회의 및 협업",
        "source_url": "",
        "source_type": "industry_report",
        "verified": false
      },
      {
        "name": "Feishu",
        "use_case": "팀 문서화 및 프로젝트 관리",
        "source_url": "",
        "source_type": "industry_report",
        "verified": false
      }
    ],
    "updated_at": "2026-02-19"
  },
  {
    "company": "NVIDIA",
    "domain": "nvidia.com",
    "industry": "Semiconductor/AI",
    "tools": [
      {
        "name": "Slack",
        "use_case": "엔지니어링 및 연구팀 협업",
        "source_url": "",
        "source_type": "industry_report",
        "verified": false
      },
      {
        "name": "Jira",
        "use_case": "GPU 및 AI 칩 개발 프로젝트 관리",
        "source_url": "",
        "source_type": "industry_report",
        "verified": false
      }
    ],
    "updated_at": "2026-02-19"
  },
  {
    "company": "Oracle",
    "domain": "oracle.com",
    "industry": "Enterprise Software",
    "tools": [
      {
        "name": "Microsoft Teams",
        "use_case": "엔터프라이즈 커뮤니케이션",
        "source_url": "https://customers.microsoft.com/en-us/story/oracle",
        "source_type": "vendor_case_study",
        "source_title": "Oracle modernizes with Microsoft 365",
        "verified": true
      },
      {
        "name": "Jira",
        "use_case": "소프트웨어 개발 관리",
        "source_url": "",
        "source_type": "industry_report",
        "verified": false
      }
    ],
    "updated_at": "2026-02-19"
  },
  {
    "company": "Salesforce",
    "domain": "salesforce.com",
    "industry": "CRM/Cloud",
    "tools": [
      {
        "name": "Slack",
        "use_case": "Slack 인수 후 Salesforce 생태계 통합",
        "source_url": "https://slack.com/customer-stories/salesforce",
        "source_type": "vendor_case_study",
        "source_title": "Salesforce and Slack: Better together",
        "verified": true
      },
      {
        "name": "Quip",
        "use_case": "문서 협업 (Salesforce 자사 제품)",
        "source_url": "",
        "source_type": "industry_report",
        "verified": false
      }
    ],
    "updated_at": "2026-02-19"
  },
  {
    "company": "ServiceNow",
    "domain": "servicenow.com",
    "industry": "Enterprise Software",
    "tools": [
      {
        "name": "Slack",
        "use_case": "내부 팀 협업 및 고객 커뮤니케이션",
        "source_url": "https://slack.com/customer-stories/servicenow",
        "source_type": "vendor_case_study",
        "source_title": "ServiceNow streamlines collaboration with Slack",
        "verified": true
      },
      {
        "name": "Microsoft Teams",
        "use_case": "엔터프라이즈 커뮤니케이션",
        "source_url": "",
        "source_type": "industry_report",
        "verified": false
      }
    ],
    "updated_at": "2026-02-19"
  },
  {
    "company": "Workday",
    "domain": "workday.com",
    "industry": "HR/Finance SaaS",
    "tools": [
      {
        "name": "Slack",
        "use_case": "HR 및 재무 팀 협업",
        "source_url": "",
        "source_type": "industry_report",
        "verified": false
      },
      {
        "name": "Jira",
        "use_case": "제품 개발 스프린트 관리",
        "source_url": "",
        "source_type": "industry_report",
        "verified": false
      }
    ],
    "updated_at": "2026-02-19"
  },
  {
    "company": "Zoom",
    "domain": "zoom.us",
    "industry": "Communication",
    "tools": [
      {
        "name": "Slack",
        "use_case": "내부 팀 협업",
        "source_url": "",
        "source_type": "industry_report",
        "verified": false
      },
      {
        "name": "Jira",
        "use_case": "비디오 플랫폼 개발 관리",
        "source_url": "",
        "source_type": "industry_report",
        "verified": false
      }
    ],
    "updated_at": "2026-02-19"
  },
  {
    "company": "Twilio",
    "domain": "twilio.com",
    "industry": "Communication API",
    "tools": [
      {
        "name": "Slack",
        "use_case": "개발자 관계 및 엔지니어링 팀 협업",
        "source_url": "https://slack.com/customer-stories/twilio",
        "source_type": "vendor_case_study",
        "source_title": "Twilio scales developer relations with Slack",
        "verified": true
      },
      {
        "name": "Notion",
        "use_case": "내부 문서 및 위키",
        "source_url": "",
        "source_type": "industry_report",
        "verified": false
      }
    ],
    "updated_at": "2026-02-19"
  },
  {
    "company": "Square (Block)",
    "domain": "block.xyz",
    "industry": "Fintech",
    "tools": [
      {
        "name": "Slack",
        "use_case": "핀테크 팀 협업",
        "source_url": "https://slack.com/customer-stories/square",
        "source_type": "vendor_case_study",
        "source_title": "Square powers collaboration with Slack",
        "verified": true
      },
      {
        "name": "Jira",
        "use_case": "결제 서비스 개발 관리",
        "source_url": "",
        "source_type": "industry_report",
        "verified": false
      }
    ],
    "updated_at": "2026-02-19"
  },
  {
    "company": "PayPal",
    "domain": "paypal.com",
    "industry": "Fintech/Payments",
    "tools": [
      {
        "name": "Microsoft Teams",
        "use_case": "글로벌 금융 팀 협업",
        "source_url": "https://customers.microsoft.com/en-us/story/paypal",
        "source_type": "vendor_case_study",
        "source_title": "PayPal enhances collaboration with Microsoft 365",
        "verified": true
      },
      {
        "name": "Jira",
        "use_case": "결제 플랫폼 개발",
        "source_url": "",
        "source_type": "industry_report",
        "verified": false
      }
    ],
    "updated_at": "2026-02-19"
  },
  {
    "company": "Visa",
    "domain": "visa.com",
    "industry": "Financial Services",
    "tools": [
      {
        "name": "Microsoft Teams",
        "use_case": "금융 서비스 팀 협업",
        "source_url": "https://customers.microsoft.com/en-us/story/visa",
        "source_type": "vendor_case_study",
        "source_title": "Visa secures collaboration with Microsoft 365",
        "verified": true
      },
      {
        "name": "Slack",
        "use_case": "혁신 및 기술 팀 소통",
        "source_url": "",
        "source_type": "industry_report",
        "verified": false
      }
    ],
    "updated_at": "2026-02-19"
  },
  {
    "company": "Mastercard",
    "domain": "mastercard.com",
    "industry": "Financial Services",
    "tools": [
      {
        "name": "Microsoft Teams",
        "use_case": "전사 협업 플랫폼",
        "source_url": "",
        "source_type": "industry_report",
        "verified": false
      },
      {
        "name": "Slack",
        "use_case": "기술 및 혁신 팀",
        "source_url": "",
        "source_type": "industry_report",
        "verified": false
      }
    ],
    "updated_at": "2026-02-19"
  },
  {
    "company": "JPMorgan Chase",
    "domain": "jpmorganchase.com",
    "industry": "Banking",
    "tools": [
      {
        "name": "Microsoft Teams",
        "use_case": "금융 서비스 및 리스크 관리 팀 협업",
        "source_url": "https://customers.microsoft.com/en-us/story/jpmorgan-chase",
        "source_type": "vendor_case_study",
        "source_title": "JPMorgan Chase transforms with Microsoft 365",
        "verified": true
      },
      {
        "name": "Slack",
        "use_case": "기술 및 엔지니어링 팀",
        "source_url": "",
        "source_type": "industry_report",
        "verified": false
      }
    ],
    "updated_at": "2026-02-19"
  },
  {
    "company": "Goldman Sachs",
    "domain": "goldmansachs.com",
    "industry": "Investment Banking",
    "tools": [
      {
        "name": "Microsoft Teams",
        "use_case": "투자 은행 팀 협업",
        "source_url": "",
        "source_type": "industry_report",
        "verified": false
      },
      {
        "name": "Slack",
        "use_case": "기술 및 데이터 팀",
        "source_url": "",
        "source_type": "industry_report",
        "verified": false
      }
    ],
    "updated_at": "2026-02-19"
  },
  {
    "company": "Morgan Stanley",
    "domain": "morganstanley.com",
    "industry": "Investment Banking",
    "tools": [
      {
        "name": "Microsoft Teams",
        "use_case": "웰스 및 리치 팀 협업",
        "source_url": "https://customers.microsoft.com/en-us/story/morgan-stanley",
        "source_type": "vendor_case_study",
        "source_title": "Morgan Stanley enhances collaboration with Microsoft 365",
        "verified": true
      }
    ],
    "updated_at": "2026-02-19"
  },
  {
    "company": "Bank of America",
    "domain": "bankofamerica.com",
    "industry": "Banking",
    "tools": [
      {
        "name": "Microsoft Teams",
        "use_case": "전사 협업 및 고객 서비스",
        "source_url": "",
        "source_type": "industry_report",
        "verified": false
      },
      {
        "name": "Slack",
        "use_case": "기술 혁신 팀",
        "source_url": "",
        "source_type": "industry_report",
        "verified": false
      }
    ],
    "updated_at": "2026-02-19"
  },
  {
    "company": "Walmart",
    "domain": "walmart.com",
    "industry": "Retail",
    "tools": [
      {
        "name": "Microsoft Teams",
        "use_case": "글로벌 리팀 협업",
        "source_url": "https://customers.microsoft.com/en-us/story/walmart",
        "source_type": "vendor_case_study",
        "source_title": "Walmart connects teams with Microsoft 365",
        "verified": true
      },
      {
        "name": "Slack",
        "use_case": "e커머스 및 디지털 혁신 팀",
        "source_url": "",
        "source_type": "industry_report",
        "verified": false
      }
    ],
    "updated_at": "2026-02-19"
  },
  {
    "company": "Costco",
    "domain": "costco.com",
    "industry": "Retail",
    "tools": [
      {
        "name": "Microsoft Teams",
        "use_case": "운영 및 공급망 팀 협업",
        "source_url": "",
        "source_type": "industry_report",
        "verified": false
      },
      {
        "name": "Slack",
        "use_case": "디지털 트랜스포메이션 팀",
        "source_url": "",
        "source_type": "industry_report",
        "verified": false
      }
    ],
    "updated_at": "2026-02-19"
  },
  {
    "company": "Target",
    "domain": "target.com",
    "industry": "Retail",
    "tools": [
      {
        "name": "Slack",
        "use_case": "리팀 및 디자인 협업",
        "source_url": "https://slack.com/customer-stories/target",
        "source_type": "vendor_case_study",
        "source_title": "Target powers retail innovation with Slack",
        "verified": true
      },
      {
        "name": "Jira",
        "use_case": "프로젝트 관리",
        "source_url": "",
        "source_type": "industry_report",
        "verified": false
      }
    ],
    "updated_at": "2026-02-19"
  },
  {
    "company": "Home Depot",
    "domain": "homedepot.com",
    "industry": "Retail",
    "tools": [
      {
        "name": "Microsoft Teams",
        "use_case": "글로벌 리팀 협업",
        "source_url": "",
        "source_type": "industry_report",
        "verified": false
      },
      {
        "name": "Slack",
        "use_case": "기술 및 e커머스 팀",
        "source_url": "",
        "source_type": "industry_report",
        "verified": false
      }
    ],
    "updated_at": "2026-02-19"
  },
  {
    "company": "McDonald's",
    "domain": "mcdonalds.com",
    "industry": "Food Service",
    "tools": [
      {
        "name": "Microsoft Teams",
        "use_case": "프랜차이즈 운영 및 본사 협업",
        "source_url": "",
        "source_type": "industry_report",
        "verified": false
      },
      {
        "name": "Slack",
        "use_case": "마케팅 및 디지털 팀",
        "source_url": "",
        "source_type": "industry_report",
        "verified": false
      }
    ],
    "updated_at": "2026-02-19"
  },
  {
    "company": "Coca-Cola",
    "domain": "coca-colacompany.com",
    "industry": "Beverages",
    "tools": [
      {
        "name": "Microsoft Teams",
        "use_case": "글로벌 마케팅 및 브랜드 팀 협업",
        "source_url": "https://customers.microsoft.com/en-us/story/coca-cola",
        "source_type": "vendor_case_study",
        "source_title": "Coca-Cola collaborates globally with Microsoft 365",
        "verified": true
      },
      {
        "name": "Slack",
        "use_case": "혁신 및 디지털 팀",
        "source_url": "",
        "source_type": "industry_report",
        "verified": false
      }
    ],
    "updated_at": "2026-02-19"
  },
  {
    "company": "PepsiCo",
    "domain": "pepsico.com",
    "industry": "Food/Beverages",
    "tools": [
      {
        "name": "Microsoft Teams",
        "use_case": "글로벌 브랜드 및 운영 팀 협업",
        "source_url": "",
        "source_type": "industry_report",
        "verified": false
      },
      {
        "name": "Slack",
        "use_case": "R&D 및 혁신 팀",
        "source_url": "",
        "source_type": "industry_report",
        "verified": false
      }
    ],
    "updated_at": "2026-02-19"
  },
  {
    "company": "Procter & Gamble",
    "domain": "pg.com",
    "industry": "Consumer Goods",
    "tools": [
      {
        "name": "Microsoft Teams",
        "use_case": "글로벌 브랜드 관리 팀 협업",
        "source_url": "",
        "source_type": "industry_report",
        "verified": false
      },
      {
        "name": "Slack",
        "use_case": "R&D 및 혁신 팀",
        "source_url": "",
        "source_type": "industry_report",
        "verified": false
      }
    ],
    "updated_at": "2026-02-19"
  },
  {
    "company": "Johnson & Johnson",
    "domain": "jnj.com",
    "industry": "Healthcare/Pharma",
    "tools": [
      {
        "name": "Microsoft Teams",
        "use_case": "제약 연구 및 개발 팀 협업",
        "source_url": "https://customers.microsoft.com/en-us/story/johnson-johnson",
        "source_type": "vendor_case_study",
        "source_title": "Johnson & Johnson accelerates research with Microsoft 365",
        "verified": true
      },
      {
        "name": "Slack",
        "use_case": "혁신 및 데이터 팀",
        "source_url": "",
        "source_type": "industry_report",
        "verified": false
      }
    ],
    "updated_at": "2026-02-19"
  },
  {
    "company": "Pfizer",
    "domain": "pfizer.com",
    "industry": "Healthcare/Pharma",
    "tools": [
      {
        "name": "Microsoft Teams",
        "use_case": "임상 시험 및 연구 팀 협업",
        "source_url": "",
        "source_type": "industry_report",
        "verified": false
      },
      {
        "name": "Slack",
        "use_case": "R&D 팀",
        "source_url": "",
        "source_type": "industry_report",
        "verified": false
      }
    ],
    "updated_at": "2026-02-19"
  },
  {
    "company": "Moderna",
    "domain": "moderna.com",
    "industry": "Biotechnology",
    "tools": [
      {
        "name": "Microsoft Teams",
        "use_case": "mRNA 백신 개발 팀 협업",
        "source_url": "",
        "source_type": "industry_report",
        "verified": false
      },
      {
        "name": "Slack",
        "use_case": "연구 및 개발 팀",
        "source_url": "",
        "source_type": "industry_report",
        "verified": false
      }
    ],
    "updated_at": "2026-02-19"
  },
  {
    "company": "IBM",
    "domain": "ibm.com",
    "industry": "Technology/Consulting",
    "tools": [
      {
        "name": "Slack",
        "use_case": "컨설팅 및 클라우드 팀 협업",
        "source_url": "https://slack.com/customer-stories/ibm",
        "source_type": "vendor_case_study",
        "source_title": "IBM modernizes collaboration with Slack",
        "verified": true
      },
      {
        "name": "Microsoft Teams",
        "use_case": "엔터프라이즈 고객 지원",
        "source_url": "",
        "source_type": "industry_report",
        "verified": false
      }
    ],
    "updated_at": "2026-02-19"
  },
  {
    "company": "Intel",
    "domain": "intel.com",
    "industry": "Semiconductor",
    "tools": [
      {
        "name": "Slack",
        "use_case": "반도체 개발 및 엔지니어링 팀 협업",
        "source_url": "",
        "source_type": "industry_report",
        "verified": false
      },
      {
        "name": "Jira",
        "use_case": "칩 개발 프로젝트 관리",
        "source_url": "",
        "source_type": "industry_report",
        "verified": false
      }
    ],
    "updated_at": "2026-02-19"
  },
  {
    "company": "AMD",
    "domain": "amd.com",
    "industry": "Semiconductor",
    "tools": [
      {
        "name": "Slack",
        "use_case": "GPU 및 CPU 개발 팀 협업",
        "source_url": "",
        "source_type": "industry_report",
        "verified": false
      },
      {
        "name": "Jira",
        "use_case": "프로세서 개발 관리",
        "source_url": "",
        "source_type": "industry_report",
        "verified": false
      }
    ],
    "updated_at": "2026-02-19"
  },
  {
    "company": "Cisco",
    "domain": "cisco.com",
    "industry": "Networking",
    "tools": [
      {
        "name": "Webex",
        "use_case": "사내 화상회의 및 협업 (자사 제품)",
        "source_url": "",
        "source_type": "industry_report",
        "verified": false
      },
      {
        "name": "Slack",
        "use_case": "팀 커뮤니케이션",
        "source_url": "",
        "source_type": "industry_report",
        "verified": false
      }
    ],
    "updated_at": "2026-02-19"
  },
  {
    "company": "VMware",
    "domain": "vmware.com",
    "industry": "Cloud/Virtualization",
    "tools": [
      {
        "name": "Slack",
        "use_case": "클라우드 및 가상화 팀 협업",
        "source_url": "https://slack.com/customer-stories/vmware",
        "source_type": "vendor_case_study",
        "source_title": "VMware connects teams with Slack",
        "verified": true
      },
      {
        "name": "Microsoft Teams",
        "use_case": "엔터프라이즈 협업",
        "source_url": "",
        "source_type": "industry_report",
        "verified": false
      }
    ],
    "updated_at": "2026-02-19"
  },
  {
    "company": "Dell Technologies",
    "domain": "dell.com",
    "industry": "Hardware",
    "tools": [
      {
        "name": "Microsoft Teams",
        "use_case": "글로벌 하드웨어 팀 협업",
        "source_url": "",
        "source_type": "industry_report",
        "verified": false
      },
      {
        "name": "Slack",
        "use_case": "기술 및 엔지니어링 팀",
        "source_url": "",
        "source_type": "industry_report",
        "verified": false
      }
    ],
    "updated_at": "2026-02-19"
  },
  {
    "company": "HP Inc.",
    "domain": "hp.com",
    "industry": "Hardware/Printing",
    "tools": [
      {
        "name": "Microsoft Teams",
        "use_case": "프린팅 및 PC 개발 팀 협업",
        "source_url": "",
        "source_type": "industry_report",
        "verified": false
      },
      {
        "name": "Slack",
        "use_case": "혁신 및 디자인 팀",
        "source_url": "",
        "source_type": "industry_report",
        "verified": false
      }
    ],
    "updated_at": "2026-02-19"
  },
  {
    "company": "Sony",
    "domain": "sony.com",
    "industry": "Electronics/Entertainment",
    "tools": [
      {
        "name": "Microsoft Teams",
        "use_case": "전자 및 엔터테인먼트 팀 협업",
        "source_url": "",
        "source_type": "industry_report",
        "verified": false
      },
      {
        "name": "Slack",
        "use_case": "게임 및 미디어 팀",
        "source_url": "",
        "source_type": "industry_report",
        "verified": false
      }
    ],
    "updated_at": "2026-02-19"
  },
  {
    "company": "Disney",
    "domain": "disney.com",
    "industry": "Entertainment/Media",
    "tools": [
      {
        "name": "Microsoft Teams",
        "use_case": "미디어 및 엔터테인먼트 팀 협업",
        "source_url": "https://customers.microsoft.com/en-us/story/disney",
        "source_type": "vendor_case_study",
        "source_title": "Disney collaborates with Microsoft 365",
        "verified": true
      },
      {
        "name": "Slack",
        "use_case": "크리에이티브 및 프로덕션 팀",
        "source_url": "",
        "source_type": "industry_report",
        "verified": false
      }
    ],
    "updated_at": "2026-02-19"
  },
  {
    "company": "DoorDash",
    "domain": "doordash.com",
    "industry": "Delivery",
    "tools": [
      {
        "name": "Slack",
        "use_case": "배달 및 물류 팀 협업",
        "source_url": "https://slack.com/customer-stories/doordash",
        "source_type": "vendor_case_study",
        "source_title": "DoorDash scales operations with Slack",
        "verified": true
      },
      {
        "name": "Jira",
        "use_case": "프로덕트 개발 관리",
        "source_url": "",
        "source_type": "industry_report",
        "verified": false
      }
    ],
    "updated_at": "2026-02-19"
  },
  {
    "company": "Lyft",
    "domain": "lyft.com",
    "industry": "Mobility",
    "tools": [
      {
        "name": "Slack",
        "use_case": "라이드셰어 팀 협업",
        "source_url": "https://slack.com/customer-stories/lyft",
        "source_type": "vendor_case_study",
        "source_title": "Lyft collaborates with Slack",
        "verified": true
      },
      {
        "name": "Jira",
        "use_case": "프로덕트 개발",
        "source_url": "",
        "source_type": "industry_report",
        "verified": false
      }
    ],
    "updated_at": "2026-02-19"
  },
  {
    "company": "Booking Holdings",
    "domain": "bookingholdings.com",
    "industry": "Travel",
    "tools": [
      {
        "name": "Microsoft Teams",
        "use_case": "여행 및 호텔 예약 팀 협업",
        "source_url": "",
        "source_type": "industry_report",
        "verified": false
      },
      {
        "name": "Slack",
        "use_case": "기술 및 프로덕트 팀",
        "source_url": "",
        "source_type": "industry_report",
        "verified": false
      }
    ],
    "updated_at": "2026-02-19"
  },
  {
    "company": "SK",
    "domain": "sk.com",
    "industry": "Conglomerate",
    "tools": [
      {
        "name": "Microsoft Teams",
        "use_case": "SK 그룹 전사 협업 플랫폼",
        "source_url": "https://customers.microsoft.com/en-us/story/sk-hynix",
        "source_type": "vendor_case_study",
        "source_title": "SK hynix collaborates with Microsoft 365",
        "verified": true
      },
      {
        "name": "Slack",
        "use_case": "혁신 및 R&D 팀",
        "source_url": "",
        "source_type": "industry_report",
        "verified": false
      }
    ],
    "updated_at": "2026-02-19"
  },
  {
    "company": "SK hynix",
    "domain": "skhynix.com",
    "industry": "Semiconductor",
    "tools": [
      {
        "name": "Microsoft Teams",
        "use_case": "메모리 반도체 개발 팀 협업",
        "source_url": "https://customers.microsoft.com/en-us/story/sk-hynix",
        "source_type": "vendor_case_study",
        "source_title": "SK hynix collaborates with Microsoft 365",
        "verified": true
      }
    ],
    "updated_at": "2026-02-19"
  },
  {
    "company": "POSCO",
    "domain": "posco.com",
    "industry": "Steel/Manufacturing",
    "tools": [
      {
        "name": "Microsoft Teams",
        "use_case": "제조 및 글로벌 영업팀 협업",
        "source_url": "",
        "source_type": "industry_report",
        "verified": false
      },
      {
        "name": "Slack",
        "use_case": "혁신 및 R&D 팀",
        "source_url": "",
        "source_type": "industry_report",
        "verified": false
      }
    ],
    "updated_at": "2026-02-19"
  },
  {
    "company": "LG Chem",
    "domain": "lgchem.com",
    "industry": "Chemicals",
    "tools": [
      {
        "name": "Microsoft Teams",
        "use_case": "배터리 및 화학 팀 협업",
        "source_url": "",
        "source_type": "industry_report",
        "verified": false
      },
      {
        "name": "Slack",
        "use_case": "R&D 및 혁신 팀",
        "source_url": "",
        "source_type": "industry_report",
        "verified": false
      }
    ],
    "updated_at": "2026-02-19"
  },
  {
    "company": "Hyundai Motor",
    "domain": "hyundai.com",
    "industry": "Automotive",
    "tools": [
      {
        "name": "Microsoft Teams",
        "use_case": "글로벌 자동차 개발 팀 협업",
        "source_url": "",
        "source_type": "industry_report",
        "verified": false
      }
    ],
    "updated_at": "2026-02-19"
  },
  {
    "company": "Kia",
    "domain": "kia.com",
    "industry": "Automotive",
    "tools": [
      {
        "name": "Microsoft Teams",
        "use_case": "글로벌 차량 개발 팀 협업",
        "source_url": "",
        "source_type": "industry_report",
        "verified": false
      },
      {
        "name": "Slack",
        "use_case": "디자인 및 혁신 팀",
        "source_url": "",
        "source_type": "industry_report",
        "verified": false
      }
    ],
    "updated_at": "2026-02-19"
  },
  {
    "company": "Samsung Electronics",
    "domain": "samsung.com",
    "industry": "Electronics",
    "tools": [
      {
        "name": "Slack",
        "use_case": "Happy Framework로 생산성 및 조직문화 개선",
        "source_url": "",
        "source_type": "industry_report",
        "verified": false
      }
    ],
    "updated_at": "2026-02-19"
  },
  {
    "company": "Samsung SDS",
    "domain": "samsungsds.com",
    "industry": "IT Services",
    "tools": [
      {
        "name": "Slack",
        "use_case": "IT 서비스 및 DX 팀 협업",
        "source_url": "",
        "source_type": "industry_report",
        "verified": false
      },
      {
        "name": "Jira",
        "use_case": "SI 프로젝트 관리",
        "source_url": "",
        "source_type": "industry_report",
        "verified": false
      }
    ],
    "updated_at": "2026-02-19"
  },
  {
    "company": "Samsung Biologics",
    "domain": "samsungbiologics.com",
    "industry": "Biotechnology",
    "tools": [
      {
        "name": "Microsoft Teams",
        "use_case": "바이오 제약 개발 팀 협업",
        "source_url": "",
        "source_type": "industry_report",
        "verified": false
      },
      {
        "name": "Jira",
        "use_case": "임상 시험 관리",
        "source_url": "",
        "source_type": "industry_report",
        "verified": false
      }
    ],
    "updated_at": "2026-02-19"
  },
  {
    "company": "LG Electronics",
    "domain": "lge.com",
    "industry": "Electronics",
    "tools": [
      {
        "name": "Microsoft Teams",
        "use_case": "가전 및 CE 팀 협업",
        "source_url": "",
        "source_type": "industry_report",
        "verified": false
      },
      {
        "name": "Slack",
        "use_case": "R&D 및 혁신 팀",
        "source_url": "",
        "source_type": "industry_report",
        "verified": false
      }
    ],
    "updated_at": "2026-02-19"
  },
  {
    "company": "LG Display",
    "domain": "lgdisplay.com",
    "industry": "Display",
    "tools": [
      {
        "name": "Microsoft Teams",
        "use_case": "디스플레이 개발 팀 협업",
        "source_url": "",
        "source_type": "industry_report",
        "verified": false
      },
      {
        "name": "Jira",
        "use_case": "패널 개발 프로젝트",
        "source_url": "",
        "source_type": "industry_report",
        "verified": false
      }
    ],
    "updated_at": "2026-02-19"
  },
  {
    "company": "Coupang",
    "domain": "coupang.com",
    "industry": "E-commerce",
    "tools": [
      {
        "name": "Slack",
        "use_case": "로켓배송 및 e커머스 팀 협업",
        "source_url": "",
        "source_type": "industry_report",
        "verified": false
      },
      {
        "name": "Jira",
        "use_case": "물류 시스템 개발",
        "source_url": "",
        "source_type": "industry_report",
        "verified": false
      }
    ],
    "updated_at": "2026-02-19"
  },
  {
    "company": "Kakao Pay",
    "domain": "kakaopay.com",
    "industry": "Fintech",
    "tools": [
      {
        "name": "Slack",
        "use_case": "핀테크 및 결제 팀 협업",
        "source_url": "",
        "source_type": "industry_report",
        "verified": false
      },
      {
        "name": "Jira",
        "use_case": "결제 서비스 개발",
        "source_url": "",
        "source_type": "industry_report",
        "verified": false
      }
    ],
    "updated_at": "2026-02-19"
  },
  {
    "company": "Kakao Bank",
    "domain": "kakaobank.com",
    "industry": "Banking",
    "tools": [
      {
        "name": "Slack",
        "use_case": "인터넷 은행 팀 협업",
        "source_url": "",
        "source_type": "industry_report",
        "verified": false
      },
      {
        "name": "Jira",
        "use_case": "뱅킹 서비스 개발",
        "source_url": "",
        "source_type": "industry_report",
        "verified": false
      }
    ],
    "updated_at": "2026-02-19"
  },
  {
    "company": "Toss (Viva Republica)",
    "domain": "toss.im",
    "industry": "Fintech",
    "tools": [
      {
        "name": "Slack",
        "use_case": "핀테크 팀 협업",
        "source_url": "",
        "source_type": "industry_report",
        "verified": false
      },
      {
        "name": "Jira",
        "use_case": "금융 서비스 개발",
        "source_url": "",
        "source_type": "industry_report",
        "verified": false
      },
      {
        "name": "Notion",
        "use_case": "내부 문서 및 위키",
        "source_url": "",
        "source_type": "industry_report",
        "verified": false
      }
    ],
    "updated_at": "2026-02-19"
  },
  {
    "company": "Woowa Brothers (Baemin)",
    "domain": "woowahan.com",
    "industry": "Delivery",
    "tools": [
      {
        "name": "Slack",
        "use_case": "배달 앱 개발 팀 협업",
        "source_url": "",
        "source_type": "industry_report",
        "verified": false
      },
      {
        "name": "Jira",
        "use_case": "배달 플랫폼 개발",
        "source_url": "",
        "source_type": "industry_report",
        "verified": false
      }
    ],
    "updated_at": "2026-02-19"
  },
  {
    "company": "Yanolja",
    "domain": "yanolja.com",
    "industry": "Travel",
    "tools": [
      {
        "name": "Slack",
        "use_case": "숙박 및 여행 팀 협업",
        "source_url": "",
        "source_type": "industry_report",
        "verified": false
      },
      {
        "name": "Jira",
        "use_case": "여행 플랫폼 개발",
        "source_url": "",
        "source_type": "industry_report",
        "verified": false
      }
    ],
    "updated_at": "2026-02-19"
  },
  {
    "company": "Ably",
    "domain": "ably.co.kr",
    "industry": "E-commerce",
    "tools": [
      {
        "name": "Slack",
        "use_case": "쇼핑 플랫폼 팀 협업",
        "source_url": "",
        "source_type": "industry_report",
        "verified": false
      },
      {
        "name": "Jira",
        "use_case": "라이브 커머스 개발",
        "source_url": "",
        "source_type": "industry_report",
        "verified": false
      }
    ],
    "updated_at": "2026-02-19"
  },
  {
    "company": "Nineton",
    "domain": "29cm.co.kr",
    "industry": "E-commerce",
    "tools": [
      {
        "name": "Slack",
        "use_case": "패션 플랫폼 팀 협업",
        "source_url": "",
        "source_type": "industry_report",
        "verified": false
      },
      {
        "name": "Notion",
        "use_case": "디자인 및 상품 기획",
        "source_url": "",
        "source_type": "industry_report",
        "verified": false
      }
    ],
    "updated_at": "2026-02-19"
  },
  {
    "company": "Musinsa",
    "domain": "musinsa.com",
    "industry": "Fashion/E-commerce",
    "tools": [
      {
        "name": "Slack",
        "use_case": "패션 플랫폼 팀 협업",
        "source_url": "",
        "source_type": "industry_report",
        "verified": false
      },
      {
        "name": "Jira",
        "use_case": "쇼핑몰 개발",
        "source_url": "",
        "source_type": "industry_report",
        "verified": false
      }
    ],
    "updated_at": "2026-02-19"
  },
  {
    "company": "Siemens",
    "domain": "siemens.com",
    "industry": "Industrial/Manufacturing",
    "tools": [
      {
        "name": "Microsoft Teams",
        "use_case": "글로벌 산업 자동화 팀 협업",
        "source_url": "https://customers.microsoft.com/en-us/story/siemens",
        "source_type": "vendor_case_study",
        "source_title": "Siemens drives innovation with Microsoft 365",
        "verified": true
      },
      {
        "name": "Slack",
        "use_case": "R&D 및 혁신 팀",
        "source_url": "",
        "source_type": "industry_report",
        "verified": false
      }
    ],
    "updated_at": "2026-02-19"
  },
  {
    "company": "General Electric",
    "domain": "ge.com",
    "industry": "Industrial/Manufacturing",
    "tools": [
      {
        "name": "Microsoft Teams",
        "use_case": "글로벌 산업 및 헬스케어 팀 협업",
        "source_url": "https://customers.microsoft.com/en-us/story/general-electric",
        "source_type": "vendor_case_study",
        "source_title": "General Electric collaborates with Microsoft 365",
        "verified": true
      }
    ],
    "updated_at": "2026-02-19"
  },
  {
    "company": "Toyota",
    "domain": "toyota-global.com",
    "industry": "Automotive",
    "tools": [
      {
        "name": "Microsoft Teams",
        "use_case": "글로벌 자동차 제조 및 R&D 팀 협업",
        "source_url": "",
        "source_type": "industry_report",
        "verified": false
      },
      {
        "name": "Slack",
        "use_case": "혁신 및 연결성 팀",
        "source_url": "",
        "source_type": "industry_report",
        "verified": false
      }
    ],
    "updated_at": "2026-02-19"
  },
  {
    "company": "Volkswagen",
    "domain": "volkswagen.com",
    "industry": "Automotive",
    "tools": [
      {
        "name": "Microsoft Teams",
        "use_case": "글로벌 차량 개발 및 제조 팀 협업",
        "source_url": "https://customers.microsoft.com/en-us/story/volkswagen",
        "source_type": "vendor_case_study",
        "source_title": "Volkswagen drives mobility with Microsoft 365",
        "verified": true
      }
    ],
    "updated_at": "2026-02-19"
  },
  {
    "company": "Accenture",
    "domain": "accenture.com",
    "industry": "Consulting",
    "tools": [
      {
        "name": "Microsoft Teams",
        "use_case": "글로벌 컨설팅 팀 협업",
        "source_url": "https://customers.microsoft.com/en-us/story/accenture",
        "source_type": "vendor_case_study",
        "source_title": "Accenture empowers teams with Microsoft 365",
        "verified": true
      },
      {
        "name": "Slack",
        "use_case": "혁신 및 기술 팀",
        "source_url": "",
        "source_type": "industry_report",
        "verified": false
      }
    ],
    "updated_at": "2026-02-19"
  },
  {
    "company": "Deloitte",
    "domain": "deloitte.com",
    "industry": "Consulting",
    "tools": [
      {
        "name": "Microsoft Teams",
        "use_case": "글로벌 전문 서비스 팀 협업",
        "source_url": "https://customers.microsoft.com/en-us/story/deloitte",
        "source_type": "vendor_case_study",
        "source_title": "Deloitte transforms collaboration with Microsoft 365",
        "verified": true
      }
    ],
    "updated_at": "2026-02-19"
  }
]